busie_flask/__init__.py
busie_flask/auth.py
busie_flask/cache.py
busie_flask/loaders.py
tests/__init__.py
tests/conftest.py
tests/test_auth.py
tests/test_cache.py
tests/test_flask_helper.py
tests/test_loaders.py
busie_flask_helper-2.2.2.dist-info/LICENSE
busie_flask_helper-2.2.2.dist-info/METADATA
busie_flask_helper-2.2.2.dist-info/WHEEL
busie_flask_helper-2.2.2.dist-info/top_level.txt
busie_flask_helper-2.2.2.dist-info/RECORD
