Metadata-Version: 2.1
Name: busie-flask-helper
Version: 2.2.2
Summary: A helper for abstracting boilerplate Flask initialization code
Home-page: https://bradyperry@bitbucket.org/busie/busie-db-helper.git
Author: Brady Perry
Author-email: brady@getbusie.com
License: UNKNOWN
Platform: UNKNOWN
Classifier: Programming Language :: Python :: 3
Classifier: License :: OSI Approved :: MIT License
Classifier: Operating System :: OS Independent
Requires-Python: >=3.6
Requires-Dist: flask
Requires-Dist: flask-sqlalchemy
Requires-Dist: flask-migrate
Requires-Dist: sqlalchemy-utils
Requires-Dist: redis
Requires-Dist: python-jose
Requires-Dist: authlib
Requires-Dist: requests
